LICENSE.txt
MANIFEST.in
README.rst
setup.cfg
setup.py
sphinxcontrib/__init__.py
sphinxcontrib/makedomain.py
sphinxcontrib_makedomain.egg-info/PKG-INFO
sphinxcontrib_makedomain.egg-info/SOURCES.txt
sphinxcontrib_makedomain.egg-info/dependency_links.txt
sphinxcontrib_makedomain.egg-info/namespace_packages.txt
sphinxcontrib_makedomain.egg-info/not-zip-safe
sphinxcontrib_makedomain.egg-info/requires.txt
sphinxcontrib_makedomain.egg-info/top_level.txt