Metadata-Version: 1.1
Name: sphinxcontrib-makedomain
Version: 0.1.1
Summary: Sphinx Make Domain Extension
Home-page: http://bitbucket.org/klorenz/sphinxcontrib-makedomain
Author: Kay-Uwe (Kiwi) Lorenz
Author-email: kiwi@franka.dyndns.org
License: BSD
Download-URL: http://pypi.python.org/pypi/sphinxcontrib-makedomain
Platform: any
Classifier: Development Status :: 4 - Beta
Classifier: Environment :: Console
Classifier: Environment :: Web Environment
Classifier: Intended Audience :: Developers
Classifier: License :: OSI Approved :: BSD License
Classifier: Operating System :: OS Independent
Classifier: Programming Language :: Python
Classifier: Topic :: Documentation
Classifier: Topic :: Utilities
